{"0": "generateBarData()", "1": "getActiveChannelForOverrides()", "2": "deleteComment()", "3": "loadChannel()", "4": "loadRealtimeStats()", "5": "formatWatchTime()", "6": "formatNumber()", "7": "ChannelProvider()", "8": "replaceImageChild()", "9": "POST()", "10": "route/GET()", "11": "since()", "12": "buildPoints()", "13": "handleSelectChannel()", "14": "formatTimeAgo()", "15": "sendEditMessage()", "16": "VideoEditPage()", "17": "handleSubmit()", "18": "StatsEditor()", "19": "fmt() (EstadisticasScreen)", "20": "fmt() (ContenidoScreen)", "21": "n() (profile)", "22": "n() ([id])", "23": "Logo()", "24": "SectionHeader()", "25": "Carousel()", "26": "useRealtimeSubscription()", "27": "index (index)", "28": "video (video)", "29": "revenue (revenue)", "30": "analytics", "31": "channel (channel)", "32": "notification", "33": "index (33)", "34": "comment (comment)", "35": "video (35)", "36": "revenue (36)", "37": "channel (37)", "38": "index (38)", "39": "comment (39)", "40": "next-env.d", "41": "next.config", "42": "layout", "43": "Sidebar", "44": "PhonePreview", "45": "TabBar", "46": "PanelScreen", "47": "ComunidadScreen", "48": "IngresosScreen", "49": "supabase (supabase)", "50": "_layout", "51": "content", "52": "comments", "53": "revenue (53)", "54": "theme", "55": "CambiarCuenta", "56": "StatCard", "57": "CommentCard", "58": "supabase (58)"}